{
  "@context": "http://schema.org",
  "@type": [
    "BioChemEntity",
    "Sample"
  ],
  "identifier": [
    "SAMN02603620",
    "MMP02603620"
  ],
  "name": "Octadecabacter arcticus 238",
  "url": "https://mmp.sfb.uit.no/databases/marref/#/records/MMP02603620",
  "description": "Octadecabacter antarcticus 238.This strain was collected 350 km offshore Deadhorse; Alaska (73 01N; 148 31 W) and isolated by direct plating.",
  "dataset": [
    "PRJNA19331",
    null,
    "19331",
    "19331",
    null,
    "GCA_000155735.2",
    null,
    null
  ],
  "additionalProperty": [
    {
      "@type": "PropertyValue",
      "name": "Geographic Location (GAZ)",
      "value": "Deadhorse",
      "valueReference": [
        {
          "@type": "CategoryCode",
          "name": "Deadhorse",
          "codeValue": null,
          "url": "https://www.ebi.ac.uk/ols/ontologies/gaz/terms?iri=http%3A%2F%2Fpurl.obolibrary.org%2Fobo%2FGAZ_00002523"
        }
      ]
    },
    {
      "@type": "PropertyValue",
      "name": "Organism",
      "value": "Octadecabacter arcticus",
      "valueReference": [
        {
          "@type": "CategoryCode",
          "name": "Octadecabacter arcticus",
          "codeValue": null,
          "url": "https://www.ncbi.nlm.nih.gov/Taxonomy/Browser/wwwtax.cgi?id=391616"
        }
      ]
    }
  ]
}