{
  "@context": "http://schema.org",
  "@type": [
    "BioChemEntity",
    "Sample"
  ],
  "identifier": [
    "SAMN02954344",
    "MMP02954344.1"
  ],
  "name": "Prochlorococcus marinus bv. HNLC1",
  "url": "https://mmp.sfb.uit.no/databases/marref/#/records/MMP02954344.1",
  "description": "Prochlorococcus clades in high-nutrient, low-chlorophyll (HNLC),iron-depleted waters in the Pacific and Indian Oceans.",
  "dataset": [
    "PRJNA67829",
    null,
    "67829",
    "67829",
    null,
    "GCF_000218705.1",
    null,
    null
  ],
  "additionalProperty": [
    {
      "@type": "PropertyValue",
      "name": "Organism",
      "value": "Prochlorococcus marinus",
      "valueReference": [
        {
          "@type": "CategoryCode",
          "name": "Prochlorococcus marinus",
          "codeValue": null,
          "url": "https://www.ncbi.nlm.nih.gov/Taxonomy/Browser/wwwtax.cgi?id=1041938"
        }
      ]
    }
  ]
}